[{"id":1,"title":"Lu\u1eadt thu\u1ebf thu nh\u1eadp c\u00e1 nh\u00e2n s\u1ed1 04\/2007\/QH12 c\u1ee7a Qu\u1ed1c h\u1ed9i","short_desc":"Lu\u1eadt thu\u1ebf thu nh\u1eadp c\u00e1 nh\u00e2n s\u1ed1 04\/2007\/QH12 c\u1ee7a Qu\u1ed1c h\u1ed9i","content":null,"images":"imgs\/documentImages.jpg","serial_number":null,"Issuance_date":null,"user_id":1,"category_id":12,"file":"[\"uploads\\\/postFiles\\\/1708668938_7-042007qh12-luat-thue-thu-nhap-ca-nhan-so-042007qh12-20210525020559-e.pdf\"]","created_at":"2024-02-23T06:15:38.000000Z","updated_at":"2024-02-23T06:15:38.000000Z","status":"activated","views":0,"deleted_at":null},{"id":2,"title":"Lu\u1eadt s\u1ed1 26\/2012\/QH13 s\u1eeda \u0111\u1ed5i, b\u1ed5 sung m\u1ed9t s\u1ed1 \u0111i\u1ec1u c\u1ee7a Lu\u1eadt Thu\u1ebf thu nh\u1eadp c\u00e1 nh\u00e2n c\u1ee7a Qu\u1ed1c h\u1ed9i","short_desc":"Lu\u1eadt s\u1ed1 26\/2012\/QH13 s\u1eeda \u0111\u1ed5i, b\u1ed5 sung m\u1ed9t s\u1ed1 \u0111i\u1ec1u c\u1ee7a Lu\u1eadt Thu\u1ebf thu nh\u1eadp c\u00e1 nh\u00e2n c\u1ee7a Qu\u1ed1c h\u1ed9i","content":null,"images":"imgs\/documentImages.jpg","serial_number":null,"Issuance_date":null,"user_id":1,"category_id":12,"file":"[\"uploads\\\/postFiles\\\/1708668995_luat-sua-doi-bo-sung-luat-thue-thu-nhap-ca-nhan-2012-20210524103445-e.pdf\"]","created_at":"2024-02-23T06:16:35.000000Z","updated_at":"2024-02-23T06:16:35.000000Z","status":"activated","views":0,"deleted_at":null},{"id":3,"title":"Lu\u1eadt s\u1ed1 71\/2014\/QH13 ng\u00e0y 26\/11\/2014 dp Qu\u1ed1c h\u1ed9i kh\u00f3a XIII ban h\u00e0nh v\u1ec1 vi\u1ec7c s\u1eeda \u0111\u1ed5i, b\u1ed5 sung m\u1ed9t s\u1ed1 \u0111i\u1ec1u c\u1ee7a c\u00e1c lu\u1eadt v\u1ec1 thu\u1ebf","short_desc":"Lu\u1eadt s\u1ed1 71\/2014\/QH13 ng\u00e0y 26\/11\/2014 dp Qu\u1ed1c h\u1ed9i kh\u00f3a XIII ban h\u00e0nh v\u1ec1 vi\u1ec7c s\u1eeda \u0111\u1ed5i, b\u1ed5 sung m\u1ed9t s\u1ed1 \u0111i\u1ec1u c\u1ee7a c\u00e1c lu\u1eadt v\u1ec1 thu\u1ebf","content":null,"images":"imgs\/documentImages.jpg","serial_number":null,"Issuance_date":null,"user_id":1,"category_id":12,"file":"[\"uploads\\\/postFiles\\\/1708669166_71signed-20210524102954-e.pdf\"]","created_at":"2024-02-23T06:19:26.000000Z","updated_at":"2024-02-23T06:19:26.000000Z","status":"activated","views":0,"deleted_at":null},{"id":4,"title":"V\u0103n b\u1ea3n h\u1ee3p nh\u1ea5t 15\/VBHN-VPQH ng\u00e0y 11\/12\/2014 do V\u0103n ph\u00f2ng Qu\u1ed1c h\u1ed9i ban h\u00e0nh h\u1ee3p nh\u1ea5t Lu\u1eadt thu\u1ebf thu nh\u1eadp c\u00e1 nh\u00e2n","short_desc":"V\u0103n b\u1ea3n h\u1ee3p nh\u1ea5t 15\/VBHN-VPQH ng\u00e0y 11\/12\/2014 do V\u0103n ph\u00f2ng Qu\u1ed1c h\u1ed9i ban h\u00e0nh h\u1ee3p nh\u1ea5t Lu\u1eadt thu\u1ebf thu nh\u1eadp c\u00e1 nh\u00e2n","content":null,"images":"imgs\/documentImages.jpg","serial_number":null,"Issuance_date":null,"user_id":1,"category_id":11,"file":"[\"uploads\\\/postFiles\\\/1708669223_15-vbhn-vpqh-20210525020816-e.pdf\"]","created_at":"2024-02-23T06:20:23.000000Z","updated_at":"2024-02-23T06:20:23.000000Z","status":"activated","views":0,"deleted_at":null},{"id":5,"title":"GIA H\u1ea0N TH\u1edcI H\u1ea0N N\u1ed8P THU\u1ebe GI\u00c1 TR\u1eca GIA T\u0102NG, THU\u1ebe THU NH\u1eacP DOANH NGHI\u1ec6P, THU\u1ebe THU NH\u1eacP C\u00c1 NH\u00c2N V\u00c0 TI\u1ec0N THU\u00ca \u0110\u1ea4T TRONG N\u0102M 2022","short_desc":"GIA H\u1ea0N TH\u1edcI H\u1ea0N N\u1ed8P THU\u1ebe GI\u00c1 TR\u1eca GIA T\u0102NG, THU\u1ebe THU NH\u1eacP DOANH NGHI\u1ec6P, THU\u1ebe THU NH\u1eacP C\u00c1 NH\u00c2N V\u00c0 TI\u1ec0N THU\u00ca \u0110\u1ea4T TRONG N\u0102M 2022","content":null,"images":"imgs\/documentImages.jpg","serial_number":null,"Issuance_date":null,"user_id":1,"category_id":11,"file":"[\"uploads\\\/postFiles\\\/1708669303_34-2022-nd-cp-510087-20220805085810-e.pdf\"]","created_at":"2024-02-23T06:21:43.000000Z","updated_at":"2024-02-23T06:21:43.000000Z","status":"activated","views":0,"deleted_at":null},{"id":6,"title":"Th\u00f4ng b\u00e1o v\u1ec1 vi\u1ec7c t\u1ed5 ch\u1ee9c h\u1ed9i ngh\u1ecb t\u1eadp hu\u1ea5n quy\u1ebft to\u00e1n thu\u1ebf 2023 v\u00e0 c\u1eadp nh\u1eadt c\u00e1c ch\u00ednh s\u00e1ch thu\u1ebf","short_desc":"Th\u00f4ng b\u00e1o v\u1ec1 vi\u1ec7c t\u1ed5 ch\u1ee9c h\u1ed9i ngh\u1ecb t\u1eadp hu\u1ea5n quy\u1ebft to\u00e1n thu\u1ebf 2023 v\u00e0 c\u1eadp nh\u1eadt c\u00e1c ch\u00ednh s\u00e1ch thu\u1ebf","content":null,"images":"imgs\/documentImages.jpg","serial_number":null,"Issuance_date":null,"user_id":1,"category_id":3,"file":null,"created_at":"2024-02-23T06:41:22.000000Z","updated_at":"2024-02-23T06:41:22.000000Z","status":"activated","views":0,"deleted_at":null}]